numbers2words/__init__.py
numbers2words/eng_numbers_to_words.py
numbers2words/numbers2words.py
numbers2words/numbers_list.py
numbers2words/tam_numbers_to_words.py
numbers2words-0.1.dist-info/METADATA
numbers2words-0.1.dist-info/WHEEL
numbers2words-0.1.dist-info/top_level.txt
numbers2words-0.1.dist-info/RECORD
