Metadata-Version: 2.4
Name: numbers2words
Version: 0.1
Summary: Convert numbers to words in Tamil, and English with Indian grouping and international grouping
Home-page: https://github.com/GiridharanPonpandi/numbers2words.git
Author: Giridharan Ponpandi
Classifier: Programming Language :: Python :: 3
Classifier: Operating System :: OS Independent
Requires-Python: >=3.6
Dynamic: author
Dynamic: classifier
Dynamic: description
Dynamic: description-content-type
Dynamic: home-page
Dynamic: requires-python
Dynamic: summary
